audonnx/__init__.py
audonnx/core/__init__.py
audonnx/core/api.py
audonnx/core/function.py
audonnx/core/model.py
audonnx/core/node.py
audonnx/core/ort.py
audonnx/core/testing.py
audonnx/core/typing.py
audonnx/testing/__init__.py
audonnx-1.0.0.dist-info/licenses/LICENSE
docs/changelog.rst
docs/conf.py
docs/contributing.rst
docs/genindex.rst
docs/index.rst
docs/installation.rst
docs/usage.rst
docs/_static/test.wav
docs/_templates/autosummary/base.rst
docs/_templates/autosummary/class.rst
docs/_templates/autosummary/function.rst
docs/api-src/audonnx.rst
docs/api-src/audonnx.testing.rst
tests/conftest.py
tests/model.onnx
tests/model.yaml
tests/test.wav
tests/test_install.py
tests/test_load.py
tests/test_model.py
tests/test_node.py
audonnx-1.0.0.dist-info/METADATA
audonnx-1.0.0.dist-info/WHEEL
audonnx-1.0.0.dist-info/top_level.txt
audonnx-1.0.0.dist-info/RECORD
