Metadata-Version: 2.4
Name: audonnx
Version: 1.0.0
Summary: Deploy models in ONNX format
Author-email: Johannes Wagner <jwagner@audeering.com>, Hagen Wierstorf <hwierstorf@audeering.com>
License: MIT License
Project-URL: repository, https://github.com/audeering/audonnx/
Project-URL: documentation, https://audeering.github.io/audonnx/
Keywords: mlops,machine learning,ONNX
Classifier: Development Status :: 5 - Production/Stable
Classifier: Intended Audience :: Science/Research
Classifier: Intended Audience :: Developers
Classifier: License :: OSI Approved :: MIT License
Classifier: Operating System :: OS Independent
Classifier: Programming Language :: Python
Classifier: Programming Language :: Python :: 3
Classifier: Programming Language :: Python :: 3.10
Classifier: Programming Language :: Python :: 3.11
Classifier: Programming Language :: Python :: 3.12
Classifier: Programming Language :: Python :: 3.13
Classifier: Topic :: Scientific/Engineering
Requires-Python: >=3.10
License-File: LICENSE
Requires-Dist: audobject>=0.7.2
Requires-Dist: onnx
Requires-Dist: onnxruntime>=1.12.0
Dynamic: license-file
